mongodb_cdk_mongodb_cluster_project/__init__.py
mongodb_cdk_mongodb_cluster_project/py.typed
mongodb_cdk_mongodb_cluster_project/_jsii/__init__.py
mongodb_cdk_mongodb_cluster_project/_jsii/cluster@1.0.2.jsii.tgz
mongodb_cdk_mongodb_cluster_project-1.0.2.dist-info/LICENSE
mongodb_cdk_mongodb_cluster_project-1.0.2.dist-info/METADATA
mongodb_cdk_mongodb_cluster_project-1.0.2.dist-info/WHEEL
mongodb_cdk_mongodb_cluster_project-1.0.2.dist-info/top_level.txt
mongodb_cdk_mongodb_cluster_project-1.0.2.dist-info/RECORD
